{
  "taskId": "2026-06-27-repository-layout-tidy",
  "repo": "pantheon-base",
  "agent": {
    "tool": "codex",
    "adapter": ".agents/adapters/codex.md"
  },
  "commands": [
    {
      "command": "npm run check:docs-frontmatter",
      "cwd": "pantheon-base",
      "status": "passed",
      "durationMs": 0,
      "notes": "validated new repository layout docs and updated docs indexes"
    },
    {
      "command": "npm run check:harness-docs",
      "cwd": "pantheon-base",
      "status": "passed",
      "durationMs": 0,
      "notes": "validated local documentation links"
    },
    {
      "command": "npm run check:harness-inventory",
      "cwd": "pantheon-base",
      "status": "passed",
      "durationMs": 0,
      "notes": "validated docs and harness script inventory"
    },
    {
      "command": "npm run check:harness-method",
      "cwd": "pantheon-base",
      "status": "passed",
      "durationMs": 0,
      "notes": "validated method health after preserving config and harness paths"
    },
    {
      "command": "npm run check:harness-sync",
      "cwd": "pantheon-base",
      "status": "passed",
      "durationMs": 0,
      "notes": "validated no upstream method sync drift"
    },
    {
      "command": "npm run check:harness-adoption",
      "cwd": "pantheon-base",
      "status": "passed",
      "durationMs": 0,
      "notes": "validated implementation-scope docs change has matching task manifest and evidence"
    },
    {
      "command": "node scripts/harness/check-task-packet.mjs --root . docs/harness/tasks/2026-06-27-repository-layout-tidy.task.md",
      "cwd": "pantheon-base",
      "status": "passed",
      "durationMs": 0,
      "notes": "validated this task packet"
    },
    {
      "command": "node scripts/harness/check-evidence.mjs --root . --strict .harness/evidence/2026-06-27-repository-layout-tidy/commands.json",
      "cwd": "pantheon-base",
      "status": "passed",
      "durationMs": 0,
      "notes": "validated this evidence file"
    },
    {
      "command": "node scripts/harness/check-review.mjs --root . --strict .harness/evidence/2026-06-27-repository-layout-tidy/review.md",
      "cwd": "pantheon-base",
      "status": "passed",
      "durationMs": 0,
      "notes": "validated this review artifact"
    },
    {
      "command": "git diff --check",
      "cwd": "pantheon-base",
      "status": "passed",
      "durationMs": 0,
      "notes": "validated whitespace"
    }
  ],
  "graphChecks": {
    "usedCodeGraph": false,
    "affectedSubgraph": [
      "repo root docs -> docs/designs index -> harness adoption evidence"
    ],
    "checks": [
      "hub",
      "call-depth"
    ],
    "findings": [],
    "notes": "Repository-layout documentation only; no runtime code moved."
  },
  "browserEvidence": [],
  "runtimeSensitive": false,
  "runtimeLogs": [],
  "runtimeGap": "Not applicable; this change only updates repository layout documentation and ignore rules.",
  "linkage": {
    "taskManifest": ".harness/tasks/2026-06-27-repository-layout-tidy/manifest.json",
    "evidenceDir": ".harness/evidence/2026-06-27-repository-layout-tidy/",
    "reviewFile": ".harness/evidence/2026-06-27-repository-layout-tidy/review.md",
    "summaryFile": ".harness/evidence/2026-06-27-repository-layout-tidy/summary.md",
    "changeRef": "none",
    "planRefs": []
  },
  "knownGaps": [
    "This pass documents local ignored artifact directories but does not delete them.",
    "Stable root paths such as config, database, releases, and schema/generated remain in place to avoid breaking scripts and CI."
  ],
  "completedAt": "2026-06-27T00:00:00Z"
}
