{
  "name": "cmdb/host",
  "displayName": "主机管理",
  "description": "CMDB 主机资产管理",
  "scope": "business",
  "parentMenu": "",
  "templateLevel": "enterprise",
  "metadata": {
    "boundedContext": "CMDB/主机管理",
    "owner": "",
    "summary": "",
    "sourceMode": "database",
    "sourceDatasourceId": "current",
    "sourceDatasourceName": "当前平台库",
    "sourceTable": "biz_cmdb_host"
  },
  "model": {
    "tableName": "biz_cmdb_host",
    "modelName": "CmdbHost",
    "fields": [
      {
        "name": "hostCode",
        "type": "string",
        "label": "主机编码",
        "required": true,
        "searchable": true,
        "sortable": true,
        "visibleInList": true,
        "visibleInForm": true,
        "placeholder": "请输入主机编码",
        "labelEn": "Host code",
        "placeholderEn": "Enter host code"
      },
      {
        "name": "hostname",
        "type": "string",
        "label": "主机名",
        "required": true,
        "searchable": true,
        "sortable": true,
        "visibleInList": true,
        "visibleInForm": true,
        "placeholder": "请输入主机名",
        "labelEn": "Hostname",
        "placeholderEn": "Enter hostname"
      },
      {
        "name": "displayName",
        "type": "string",
        "label": "显示名称",
        "required": true,
        "searchable": true,
        "sortable": true,
        "visibleInList": true,
        "visibleInForm": true,
        "placeholder": "请输入显示名称",
        "labelEn": "Display name",
        "placeholderEn": "Enter display name"
      },
      {
        "name": "ipAddress",
        "type": "string",
        "label": "IP 地址",
        "required": true,
        "searchable": false,
        "sortable": true,
        "visibleInList": true,
        "visibleInForm": true,
        "placeholder": "请输入 IP 地址",
        "labelEn": "IP address",
        "placeholderEn": "Enter IP address"
      },
      {
        "name": "sshPort",
        "type": "int",
        "label": "SSH 端口",
        "required": true,
        "searchable": false,
        "sortable": true,
        "visibleInList": true,
        "visibleInForm": true,
        "placeholder": "",
        "labelEn": "SSH port"
      },
      {
        "name": "osFamily",
        "type": "string",
        "label": "系统家族",
        "required": true,
        "searchable": false,
        "sortable": true,
        "visibleInList": true,
        "visibleInForm": true,
        "placeholder": "请输入系统家族",
        "labelEn": "OS family",
        "placeholderEn": "Enter OS family"
      },
      {
        "name": "osName",
        "type": "string",
        "label": "操作系统",
        "required": true,
        "searchable": true,
        "sortable": true,
        "visibleInList": true,
        "visibleInForm": true,
        "placeholder": "请输入操作系统",
        "labelEn": "OS name",
        "placeholderEn": "Enter OS name"
      },
      {
        "name": "kernelVersion",
        "type": "string",
        "label": "内核版本",
        "required": true,
        "searchable": false,
        "sortable": true,
        "visibleInList": true,
        "visibleInForm": true,
        "placeholder": "请输入内核版本",
        "labelEn": "Kernel version",
        "placeholderEn": "Enter kernel version"
      },
      {
        "name": "arch",
        "type": "string",
        "label": "架构",
        "required": true,
        "searchable": false,
        "sortable": true,
        "visibleInList": true,
        "visibleInForm": true,
        "placeholder": "请输入架构",
        "labelEn": "Arch",
        "placeholderEn": "Enter architecture"
      },
      {
        "name": "environment",
        "type": "enum",
        "label": "环境",
        "required": true,
        "searchable": false,
        "sortable": true,
        "visibleInList": true,
        "visibleInForm": true,
        "placeholder": "请选择环境",
        "labelEn": "Environment",
        "placeholderEn": "Select environment"
      },
      {
        "name": "status",
        "type": "enum",
        "label": "状态",
        "required": true,
        "searchable": true,
        "sortable": true,
        "visibleInList": true,
        "visibleInForm": true,
        "placeholder": "请选择状态",
        "labelEn": "Status",
        "placeholderEn": "Select status"
      },
      {
        "name": "lifecycleStatus",
        "type": "string",
        "label": "生命周期状态",
        "required": true,
        "searchable": true,
        "sortable": true,
        "visibleInList": true,
        "visibleInForm": true,
        "placeholder": "请输入生命周期状态",
        "labelEn": "Lifecycle status",
        "placeholderEn": "Enter lifecycle status"
      },
      {
        "name": "provider",
        "type": "string",
        "label": "云厂商",
        "required": true,
        "searchable": false,
        "sortable": true,
        "visibleInList": true,
        "visibleInForm": true,
        "placeholder": "请输入云厂商",
        "labelEn": "Provider",
        "placeholderEn": "Enter provider"
      },
      {
        "name": "regionCode",
        "type": "string",
        "label": "区域编码",
        "required": true,
        "searchable": true,
        "sortable": true,
        "visibleInList": true,
        "visibleInForm": true,
        "placeholder": "请输入区域编码",
        "labelEn": "Region code",
        "placeholderEn": "Enter region code"
      },
      {
        "name": "idcCode",
        "type": "string",
        "label": "机房编码",
        "required": true,
        "searchable": true,
        "sortable": true,
        "visibleInList": true,
        "visibleInForm": true,
        "placeholder": "请输入机房编码",
        "labelEn": "IDC code",
        "placeholderEn": "Enter IDC code"
      },
      {
        "name": "clusterName",
        "type": "string",
        "label": "集群名称",
        "required": true,
        "searchable": true,
        "sortable": true,
        "visibleInList": true,
        "visibleInForm": true,
        "placeholder": "请输入集群名称",
        "labelEn": "Cluster name",
        "placeholderEn": "Enter cluster name"
      },
      {
        "name": "ownerUserId",
        "type": "int",
        "label": "负责人用户 ID",
        "required": true,
        "searchable": false,
        "sortable": true,
        "visibleInList": true,
        "visibleInForm": true,
        "placeholder": "",
        "labelEn": "Owner user ID"
      },
      {
        "name": "ownerName",
        "type": "string",
        "label": "负责人",
        "required": true,
        "searchable": true,
        "sortable": true,
        "visibleInList": true,
        "visibleInForm": true,
        "placeholder": "请输入负责人",
        "labelEn": "Owner name",
        "placeholderEn": "Enter owner name"
      },
      {
        "name": "maintainerTeam",
        "type": "string",
        "label": "维护团队",
        "required": true,
        "searchable": false,
        "sortable": true,
        "visibleInList": true,
        "visibleInForm": true,
        "placeholder": "请输入维护团队",
        "labelEn": "Maintainer team",
        "placeholderEn": "Enter maintainer team"
      },
      {
        "name": "purpose",
        "type": "string",
        "label": "用途",
        "required": true,
        "searchable": false,
        "sortable": true,
        "visibleInList": true,
        "visibleInForm": true,
        "placeholder": "请输入用途",
        "labelEn": "Purpose",
        "placeholderEn": "Enter purpose"
      },
      {
        "name": "lastCheckInAt",
        "type": "date",
        "label": "最近上报时间",
        "required": false,
        "searchable": false,
        "sortable": true,
        "visibleInList": true,
        "visibleInForm": true,
        "placeholder": "",
        "labelEn": "Last check-in time"
      },
      {
        "name": "lastInventoryAt",
        "type": "date",
        "label": "最近盘点时间",
        "required": false,
        "searchable": false,
        "sortable": true,
        "visibleInList": true,
        "visibleInForm": true,
        "placeholder": "",
        "labelEn": "Last inventory time"
      },
      {
        "name": "lastOperatedAt",
        "type": "date",
        "label": "最近操作时间",
        "required": false,
        "searchable": false,
        "sortable": true,
        "visibleInList": true,
        "visibleInForm": true,
        "placeholder": "",
        "labelEn": "Last operated time"
      },
      {
        "name": "remark",
        "type": "string",
        "label": "备注",
        "required": true,
        "searchable": false,
        "sortable": true,
        "visibleInList": true,
        "visibleInForm": true,
        "placeholder": "请输入备注",
        "labelEn": "Remark",
        "placeholderEn": "Enter remark"
      }
    ]
  },
  "i18n": {
    "namespace": "business.cmdb.host",
    "translations": {
      "zh": {
        "business.cmdb.title": "CMDB",
        "business.cmdb.host.audit.create": "新增主机管理",
        "business.cmdb.host.audit.delete": "删除主机管理",
        "business.cmdb.host.audit.update": "编辑主机管理",
        "business.cmdb.host.field.arch.label": "架构",
        "business.cmdb.host.field.arch.placeholder": "请输入架构",
        "business.cmdb.host.field.clusterName.label": "集群名称",
        "business.cmdb.host.field.clusterName.placeholder": "请输入集群名称",
        "business.cmdb.host.field.displayName.label": "显示名称",
        "business.cmdb.host.field.displayName.placeholder": "请输入显示名称",
        "business.cmdb.host.field.environment.label": "环境",
        "business.cmdb.host.field.environment.option.dev": "开发",
        "business.cmdb.host.field.environment.option.prod": "生产",
        "business.cmdb.host.field.environment.option.staging": "预发",
        "business.cmdb.host.field.environment.option.test": "测试",
        "business.cmdb.host.field.environment.placeholder": "请选择环境",
        "business.cmdb.host.field.hostCode.label": "主机编码",
        "business.cmdb.host.field.hostCode.placeholder": "请输入主机编码",
        "business.cmdb.host.field.hostname.label": "主机名",
        "business.cmdb.host.field.hostname.placeholder": "请输入主机名",
        "business.cmdb.host.field.idcCode.label": "机房编码",
        "business.cmdb.host.field.idcCode.placeholder": "请输入机房编码",
        "business.cmdb.host.field.ipAddress.label": "IP 地址",
        "business.cmdb.host.field.ipAddress.placeholder": "请输入 IP 地址",
        "business.cmdb.host.field.kernelVersion.label": "内核版本",
        "business.cmdb.host.field.kernelVersion.placeholder": "请输入内核版本",
        "business.cmdb.host.field.lastCheckInAt.label": "最近上报时间",
        "business.cmdb.host.field.lastInventoryAt.label": "最近盘点时间",
        "business.cmdb.host.field.lastOperatedAt.label": "最近操作时间",
        "business.cmdb.host.field.lifecycleStatus.label": "生命周期状态",
        "business.cmdb.host.field.lifecycleStatus.placeholder": "请输入生命周期状态",
        "business.cmdb.host.field.maintainerTeam.label": "维护团队",
        "business.cmdb.host.field.maintainerTeam.placeholder": "请输入维护团队",
        "business.cmdb.host.field.osFamily.label": "系统家族",
        "business.cmdb.host.field.osFamily.placeholder": "请输入系统家族",
        "business.cmdb.host.field.osName.label": "操作系统",
        "business.cmdb.host.field.osName.placeholder": "请输入操作系统",
        "business.cmdb.host.field.ownerName.label": "负责人",
        "business.cmdb.host.field.ownerName.placeholder": "请输入负责人",
        "business.cmdb.host.field.ownerUserId.label": "负责人用户 ID",
        "business.cmdb.host.field.provider.label": "云厂商",
        "business.cmdb.host.field.provider.placeholder": "请输入云厂商",
        "business.cmdb.host.field.purpose.label": "用途",
        "business.cmdb.host.field.purpose.placeholder": "请输入用途",
        "business.cmdb.host.field.regionCode.label": "区域编码",
        "business.cmdb.host.field.regionCode.placeholder": "请输入区域编码",
        "business.cmdb.host.field.remark.label": "备注",
        "business.cmdb.host.field.remark.placeholder": "请输入备注",
        "business.cmdb.host.field.sshPort.label": "SSH 端口",
        "business.cmdb.host.field.status.label": "状态",
        "business.cmdb.host.field.status.option.active": "启用",
        "business.cmdb.host.field.status.option.inactive": "停用",
        "business.cmdb.host.field.status.placeholder": "请选择状态",
        "business.cmdb.host.permission.create": "新增主机管理",
        "business.cmdb.host.permission.delete": "删除主机管理",
        "business.cmdb.host.permission.export": "导出主机管理",
        "business.cmdb.host.permission.import": "导入主机管理",
        "business.cmdb.host.permission.update": "编辑主机管理",
        "business.cmdb.host.permission.view": "查看主机管理",
        "business.cmdb.host.title": "主机管理"
      },
      "en": {
        "business.cmdb.title": "CMDB",
        "business.cmdb.host.audit.create": "Create host",
        "business.cmdb.host.audit.delete": "Delete host",
        "business.cmdb.host.audit.update": "Update host",
        "business.cmdb.host.field.arch.label": "Arch",
        "business.cmdb.host.field.arch.placeholder": "Enter architecture",
        "business.cmdb.host.field.clusterName.label": "Cluster name",
        "business.cmdb.host.field.clusterName.placeholder": "Enter cluster name",
        "business.cmdb.host.field.displayName.label": "Display name",
        "business.cmdb.host.field.displayName.placeholder": "Enter display name",
        "business.cmdb.host.field.environment.label": "Environment",
        "business.cmdb.host.field.environment.option.dev": "dev",
        "business.cmdb.host.field.environment.option.prod": "prod",
        "business.cmdb.host.field.environment.option.staging": "staging",
        "business.cmdb.host.field.environment.option.test": "test",
        "business.cmdb.host.field.environment.placeholder": "Select environment",
        "business.cmdb.host.field.hostCode.label": "Host code",
        "business.cmdb.host.field.hostCode.placeholder": "Enter host code",
        "business.cmdb.host.field.hostname.label": "Hostname",
        "business.cmdb.host.field.hostname.placeholder": "Enter hostname",
        "business.cmdb.host.field.idcCode.label": "IDC code",
        "business.cmdb.host.field.idcCode.placeholder": "Enter IDC code",
        "business.cmdb.host.field.ipAddress.label": "IP address",
        "business.cmdb.host.field.ipAddress.placeholder": "Enter IP address",
        "business.cmdb.host.field.kernelVersion.label": "Kernel version",
        "business.cmdb.host.field.kernelVersion.placeholder": "Enter kernel version",
        "business.cmdb.host.field.lastCheckInAt.label": "Last check-in time",
        "business.cmdb.host.field.lastInventoryAt.label": "Last inventory time",
        "business.cmdb.host.field.lastOperatedAt.label": "Last operated time",
        "business.cmdb.host.field.lifecycleStatus.label": "Lifecycle status",
        "business.cmdb.host.field.lifecycleStatus.placeholder": "Enter lifecycle status",
        "business.cmdb.host.field.maintainerTeam.label": "Maintainer team",
        "business.cmdb.host.field.maintainerTeam.placeholder": "Enter maintainer team",
        "business.cmdb.host.field.osFamily.label": "OS family",
        "business.cmdb.host.field.osFamily.placeholder": "Enter OS family",
        "business.cmdb.host.field.osName.label": "OS name",
        "business.cmdb.host.field.osName.placeholder": "Enter OS name",
        "business.cmdb.host.field.ownerName.label": "Owner name",
        "business.cmdb.host.field.ownerName.placeholder": "Enter owner name",
        "business.cmdb.host.field.ownerUserId.label": "Owner user ID",
        "business.cmdb.host.field.provider.label": "Provider",
        "business.cmdb.host.field.provider.placeholder": "Enter provider",
        "business.cmdb.host.field.purpose.label": "Purpose",
        "business.cmdb.host.field.purpose.placeholder": "Enter purpose",
        "business.cmdb.host.field.regionCode.label": "Region code",
        "business.cmdb.host.field.regionCode.placeholder": "Enter region code",
        "business.cmdb.host.field.remark.label": "Remark",
        "business.cmdb.host.field.remark.placeholder": "Enter remark",
        "business.cmdb.host.field.sshPort.label": "SSH port",
        "business.cmdb.host.field.status.label": "Status",
        "business.cmdb.host.field.status.option.active": "active",
        "business.cmdb.host.field.status.option.inactive": "inactive",
        "business.cmdb.host.field.status.placeholder": "Select status",
        "business.cmdb.host.permission.create": "Create hosts",
        "business.cmdb.host.permission.delete": "Delete hosts",
        "business.cmdb.host.permission.export": "Export hosts",
        "business.cmdb.host.permission.import": "Import hosts",
        "business.cmdb.host.permission.update": "Update hosts",
        "business.cmdb.host.permission.view": "View hosts",
        "business.cmdb.host.title": "Host Management"
      }
    }
  },
  "displayNameEn": "Host Management",
  "pageActionTemplate": "masterData",
  "pageActions": [
    "view",
    "detail",
    "create",
    "update",
    "delete",
    "export",
    "import"
  ],
  "menus": [
    {
      "key": "cmdb",
      "parentKey": "business",
      "titleKey": "business.cmdb.title",
      "path": "/business/cmdb",
      "type": "M",
      "icon": "apps",
      "routeName": "business-cmdb",
      "module": "business.cmdb",
      "sort": 10
    },
    {
      "key": "cmdb-host",
      "parentKey": "cmdb",
      "titleKey": "business.cmdb.host.title",
      "path": "/business/cmdb/host",
      "component": "business/cmdb/host/CmdbHostList",
      "pagePermission": "business:cmdb:host:list",
      "type": "C",
      "icon": "apps",
      "routeName": "business-cmdb-host",
      "module": "business.cmdb.host",
      "sort": 10
    },
    {
      "key": "cmdb-host-view",
      "parentKey": "cmdb-host",
      "titleKey": "business.cmdb.host.permission.view",
      "perms": "business:cmdb:host:view",
      "type": "F",
      "module": "business.cmdb.host",
      "sort": 1
    },
    {
      "key": "cmdb-host-create",
      "parentKey": "cmdb-host",
      "titleKey": "business.cmdb.host.permission.create",
      "perms": "business:cmdb:host:create",
      "type": "F",
      "module": "business.cmdb.host",
      "sort": 2
    },
    {
      "key": "cmdb-host-update",
      "parentKey": "cmdb-host",
      "titleKey": "business.cmdb.host.permission.update",
      "perms": "business:cmdb:host:update",
      "type": "F",
      "module": "business.cmdb.host",
      "sort": 3
    },
    {
      "key": "cmdb-host-delete",
      "parentKey": "cmdb-host",
      "titleKey": "business.cmdb.host.permission.delete",
      "perms": "business:cmdb:host:delete",
      "type": "F",
      "module": "business.cmdb.host",
      "sort": 4
    },
    {
      "key": "cmdb-host-export",
      "parentKey": "cmdb-host",
      "titleKey": "business.cmdb.host.permission.export",
      "perms": "business:cmdb:host:export",
      "type": "F",
      "module": "business.cmdb.host",
      "sort": 5
    },
    {
      "key": "cmdb-host-import",
      "parentKey": "cmdb-host",
      "titleKey": "business.cmdb.host.permission.import",
      "perms": "business:cmdb:host:import",
      "type": "F",
      "module": "business.cmdb.host",
      "sort": 6
    }
  ],
  "permissions": [
    {
      "key": "business:cmdb:host:list",
      "name": "business.cmdb.host.permission.view",
      "type": "menu",
      "module": "business.cmdb.host"
    },
    {
      "key": "business:cmdb:host:view",
      "name": "business.cmdb.host.permission.view",
      "type": "button",
      "module": "business.cmdb.host"
    },
    {
      "key": "business:cmdb:host:create",
      "name": "business.cmdb.host.permission.create",
      "type": "button",
      "module": "business.cmdb.host"
    },
    {
      "key": "business:cmdb:host:update",
      "name": "business.cmdb.host.permission.update",
      "type": "button",
      "module": "business.cmdb.host"
    },
    {
      "key": "business:cmdb:host:delete",
      "name": "business.cmdb.host.permission.delete",
      "type": "button",
      "module": "business.cmdb.host"
    },
    {
      "key": "business:cmdb:host:export",
      "name": "business.cmdb.host.permission.export",
      "type": "button",
      "module": "business.cmdb.host"
    },
    {
      "key": "business:cmdb:host:import",
      "name": "business.cmdb.host.permission.import",
      "type": "button",
      "module": "business.cmdb.host"
    }
  ],
  "enableExport": true,
  "enableImport": true,
  "enableAudit": true,
  "enableDataScope": false
}
